confluence_wiki_generator/__init__.py
confluence_wiki_generator/emphasis.py
confluence_wiki_generator/list.py
confluence_wiki_generator/table.py
confluence_wiki_generator/writer.py
confluence_wiki_generator-0.0.0.dist-info/LICENSE
confluence_wiki_generator-0.0.0.dist-info/METADATA
confluence_wiki_generator-0.0.0.dist-info/WHEEL
confluence_wiki_generator-0.0.0.dist-info/top_level.txt
confluence_wiki_generator-0.0.0.dist-info/RECORD
